enformer_dna_diff/__init__.py
enformer_dna_diff/enformer.py
enformer_dna_diff/enformerops.py
enformer_dna_diff/main_script.py
enformer_dna_diff/real_main_script.py
enformer_dna_diff/utils.py
enformer_dna_diff-1.4.data/scripts/get_data.py
src/__init__.py
src/enformer.py
src/enformerops.py
src/main_script.py
src/real_main_script.py
src/utils.py
enformer_dna_diff-1.4.dist-info/LICENSE
enformer_dna_diff-1.4.dist-info/METADATA
enformer_dna_diff-1.4.dist-info/WHEEL
enformer_dna_diff-1.4.dist-info/top_level.txt
enformer_dna_diff-1.4.dist-info/RECORD
